knds/__init__.py
knds/auxi.py
knds/gif.py
knds/orbit.py
knds/shadow.py
knds_orbits_and_shadows-1.35.dist-info/LICENSE.txt
knds_orbits_and_shadows-1.35.dist-info/METADATA
knds_orbits_and_shadows-1.35.dist-info/WHEEL
knds_orbits_and_shadows-1.35.dist-info/top_level.txt
knds_orbits_and_shadows-1.35.dist-info/RECORD
