Metadata-Version: 2.1
Name: knds-orbits-and-shadows
Version: 1.35
Summary: Python3 package drawing orbits and shadows of Kerr--Newman--(anti) de Sitter black holes
Home-page: https://github.com/arthur-garnier/knds_orbits_and_shadows-python
Author: Arthur Garnier
Author-email: <arthur.garnier@math.cnrs.fr>
License: UNKNOWN
Keywords: python,knds,kerr,kerr-newman,deSitter,cosmology,black hole,orbit,black hole shadowing,accretion disk,backward ray-tracing,gif
Platform: UNKNOWN
Classifier: Development Status :: 3 - Alpha
Classifier: Intended Audience :: Education
Classifier: Intended Audience :: Science/Research
Classifier: Programming Language :: Python :: 3
Classifier: Operating System :: Unix
Classifier: Operating System :: MacOS :: MacOS X
Classifier: Operating System :: Microsoft :: Windows
Classifier: License :: OSI Approved :: GNU General Public License v3 (GPLv3)
Requires-Python: >=3.10
License-File: LICENSE.txt
Requires-Dist: imageio (>=2.36)
Requires-Dist: opencv-python (>=4.10)
